{
  "generated_at": "2026-02-04T23:54:41.915373",
  "repository": "https://git.kernel.org/pub/scm/devel/sparse/sparse.git",
  "total_commits": 4652,
  "years": {
    "2003": {
      "file": "2003.json",
      "commits": 455,
      "with_description": 175,
      "without_description": 280,
      "contributors": 11
    },
    "2004": {
      "file": "2004.json",
      "commits": 911,
      "with_description": 617,
      "without_description": 294,
      "contributors": 25
    },
    "2005": {
      "file": "2005.json",
      "commits": 174,
      "with_description": 154,
      "without_description": 20,
      "contributors": 24
    },
    "2006": {
      "file": "2006.json",
      "commits": 86,
      "with_description": 76,
      "without_description": 10,
      "contributors": 14
    },
    "2007": {
      "file": "2007.json",
      "commits": 268,
      "with_description": 267,
      "without_description": 1,
      "contributors": 21
    },
    "2008": {
      "file": "2008.json",
      "commits": 51,
      "with_description": 51,
      "without_description": 0,
      "contributors": 13
    },
    "2009": {
      "file": "2009.json",
      "commits": 84,
      "with_description": 84,
      "without_description": 0,
      "contributors": 23
    },
    "2010": {
      "file": "2010.json",
      "commits": 29,
      "with_description": 29,
      "without_description": 0,
      "contributors": 10
    },
    "2011": {
      "file": "2011.json",
      "commits": 116,
      "with_description": 113,
      "without_description": 3,
      "contributors": 13
    },
    "2012": {
      "file": "2012.json",
      "commits": 29,
      "with_description": 29,
      "without_description": 0,
      "contributors": 13
    },
    "2013": {
      "file": "2013.json",
      "commits": 54,
      "with_description": 54,
      "without_description": 0,
      "contributors": 16
    },
    "2014": {
      "file": "2014.json",
      "commits": 44,
      "with_description": 44,
      "without_description": 0,
      "contributors": 15
    },
    "2015": {
      "file": "2015.json",
      "commits": 12,
      "with_description": 12,
      "without_description": 0,
      "contributors": 8
    },
    "2016": {
      "file": "2016.json",
      "commits": 97,
      "with_description": 97,
      "without_description": 0,
      "contributors": 12
    },
    "2017": {
      "file": "2017.json",
      "commits": 646,
      "with_description": 634,
      "without_description": 12,
      "contributors": 11
    },
    "2018": {
      "file": "2018.json",
      "commits": 587,
      "with_description": 575,
      "without_description": 12,
      "contributors": 11
    },
    "2019": {
      "file": "2019.json",
      "commits": 233,
      "with_description": 226,
      "without_description": 7,
      "contributors": 11
    },
    "2020": {
      "file": "2020.json",
      "commits": 570,
      "with_description": 552,
      "without_description": 18,
      "contributors": 12
    },
    "2021": {
      "file": "2021.json",
      "commits": 132,
      "with_description": 128,
      "without_description": 4,
      "contributors": 4
    },
    "2022": {
      "file": "2022.json",
      "commits": 42,
      "with_description": 42,
      "without_description": 0,
      "contributors": 4
    },
    "2023": {
      "file": "2023.json",
      "commits": 7,
      "with_description": 7,
      "without_description": 0,
      "contributors": 5
    },
    "2024": {
      "file": "2024.json",
      "commits": 19,
      "with_description": 18,
      "without_description": 1,
      "contributors": 4
    },
    "2025": {
      "file": "2025.json",
      "commits": 5,
      "with_description": 5,
      "without_description": 0,
      "contributors": 4
    },
    "2028": {
      "file": "2028.json",
      "commits": 1,
      "with_description": 1,
      "without_description": 0,
      "contributors": 1
    }
  }
}